pydab/__init__.py
pydab/cli.py
pydab/logging.yaml
pydab/pydab.py
pydab/util.py
pydab-0.0.0.dev0.dist-info/LICENSE
pydab-0.0.0.dev0.dist-info/METADATA
pydab-0.0.0.dev0.dist-info/WHEEL
pydab-0.0.0.dev0.dist-info/entry_points.txt
pydab-0.0.0.dev0.dist-info/top_level.txt
pydab-0.0.0.dev0.dist-info/RECORD
